memeticga/__init__.py
memeticga/core.py
memeticga-0.1.5.dist-info/licenses/LICENSE
memeticga-0.1.5.dist-info/METADATA
memeticga-0.1.5.dist-info/WHEEL
memeticga-0.1.5.dist-info/top_level.txt
memeticga-0.1.5.dist-info/RECORD
