Metadata-Version: 2.4
Name: memeticga
Version: 0.1.5
Summary: Ready-to-use Memetic Genetic Algorithm built on DEAP.
Author-email: kakoyvostorg <862andfurther@gmail.com>
License: MIT License
Requires-Python: >=3.8
License-File: LICENSE
Requires-Dist: numpy>=1.14.5
Requires-Dist: deap>=0.8
Requires-Dist: tqdm>=2.2.4
Provides-Extra: dev
Requires-Dist: pytest>=7.0; extra == "dev"
Requires-Dist: pytest-cov; extra == "dev"
Requires-Dist: hypothesis; extra == "dev"
Requires-Dist: ruff>=0.0.282; extra == "dev"
Requires-Dist: black>=23.0.0; extra == "dev"
Requires-Dist: isort>=5.0.0; extra == "dev"
Requires-Dist: mypy>=1.9; extra == "dev"
Requires-Dist: cloudpickle>=2.0.0; extra == "dev"
Provides-Extra: mp
Requires-Dist: cloudpickle>=2.0.0; extra == "mp"
Dynamic: license-file
